[
	{
		"inputs": [],
		"stateMutability": "nonpayable",
		"type": "constructor"
	},
	{
		"inputs": [],
		"name": "getAllCountries",
		"outputs": [
			{
				"components": [
					{
						"internalType": "uint256",
						"name": "id",
						"type": "uint256"
					},
					{
						"internalType": "string",
						"name": "name",
						"type": "string"
					},
					{
						"internalType": "string",
						"name": "capital",
						"type": "string"
					},
					{
						"internalType": "string",
						"name": "img",
						"type": "string"
					},
					{
						"internalType": "string",
						"name": "describe",
						"type": "string"
					}
				],
				"internalType": "struct Countries.Country[]",
				"name": "",
				"type": "tuple[]"
			}
		],
		"stateMutability": "view",
		"type": "function"
	},
	{
		"inputs": [],
		"name": "getCountries",
		"outputs": [
			{
				"internalType": "uint256[]",
				"name": "",
				"type": "uint256[]"
			},
			{
				"internalType": "string[]",
				"name": "",
				"type": "string[]"
			},
			{
				"internalType": "string[]",
				"name": "",
				"type": "string[]"
			},
			{
				"internalType": "string[]",
				"name": "",
				"type": "string[]"
			},
			{
				"internalType": "string[]",
				"name": "",
				"type": "string[]"
			}
		],
		"stateMutability": "view",
		"type": "function"
	},
	{
		"inputs": [],
		"name": "getTotalCountries",
		"outputs": [
			{
				"internalType": "uint256",
				"name": "",
				"type": "uint256"
			}
		],
		"stateMutability": "view",
		"type": "function"
	},
	{
		"inputs": [
			{
				"internalType": "uint256",
				"name": "_id",
				"type": "uint256"
			},
			{
				"internalType": "string",
				"name": "_name",
				"type": "string"
			},
			{
				"internalType": "string",
				"name": "_capital",
				"type": "string"
			},
			{
				"internalType": "string",
				"name": "_img",
				"type": "string"
			},
			{
				"internalType": "string",
				"name": "_describe",
				"type": "string"
			}
		],
		"name": "insertCountry",
		"outputs": [],
		"stateMutability": "nonpayable",
		"type": "function"
	},
	{
		"inputs": [
			{
				"internalType": "uint256",
				"name": "_id",
				"type": "uint256"
			},
			{
				"internalType": "string",
				"name": "_name",
				"type": "string"
			},
			{
				"internalType": "string",
				"name": "_capital",
				"type": "string"
			},
			{
				"internalType": "string",
				"name": "_img",
				"type": "string"
			},
			{
				"internalType": "string",
				"name": "_describe",
				"type": "string"
			}
		],
		"name": "updateCountries",
		"outputs": [],
		"stateMutability": "nonpayable",
		"type": "function"
	}
]